tldm/__init__.py
tldm/_monitor.py
tldm/aliases.py
tldm/logging.py
tldm/notebook.py
tldm/py.typed
tldm/std.py
tldm/utils.py
tldm/extensions/__init__.py
tldm/extensions/asyncio.py
tldm/extensions/concurrent.py
tldm/extensions/pandas.py
tldm/extensions/rich.py
tldm-1.1.1.dist-info/METADATA
tldm-1.1.1.dist-info/WHEEL
tldm-1.1.1.dist-info/licenses/LICENCE
tldm-1.1.1.dist-info/RECORD
